imppkg/py.typed
imppkg/harmony.py
imppkg/harmonic_mean_c.c
imppkg/harmonic_mean_c.pyx
imppkg/harmonic_mean_c.cpython-312-i386-linux-gnu.so
imppkg/__init__.py
imppkg/harmonic_mean.py
imppkg/hello.py
imppkg/data.json
pubpypack_harmony_cindytsai-0.0.2.dist-info/METADATA
pubpypack_harmony_cindytsai-0.0.2.dist-info/LICENSE
pubpypack_harmony_cindytsai-0.0.2.dist-info/entry_points.txt
pubpypack_harmony_cindytsai-0.0.2.dist-info/WHEEL
pubpypack_harmony_cindytsai-0.0.2.dist-info/RECORD
pubpypack_harmony_cindytsai-0.0.2.dist-info/top_level.txt
