Metadata-Version: 2.1
Name: pubpypack-harmony-cindytsai
Version: 0.0.2
Summary: This is my first python package.
Home-page: https://github.com/cindytsai/MyPythonPackage
Author: Shin-Rong Tsai
Author-email: "Shin-Rong Tsai" <turquoisea.tsai@gmail.com>
License: MIT
Classifier: License :: OSI Approved :: MIT License
Requires-Python: >=3.9
License-File: LICENSE
Requires-Dist: termcolor <3,>=2.0.0
